Metadata-Version: 2.1
Name: keras-self-attention
Version: 0.51.0
Summary: Attention mechanism for processing sequential data that considers the context for each timestamp
Home-page: https://github.com/CyberZHG/keras-self-attention
Author: CyberZHG
Author-email: CyberZHG@users.noreply.github.com
License: MIT
Platform: UNKNOWN
Classifier: Programming Language :: Python :: 3
Classifier: License :: OSI Approved :: MIT License
Classifier: Operating System :: OS Independent
